unitree_webrtc_connect/__init__.py
unitree_webrtc_connect/constants.py
unitree_webrtc_connect/encryption.py
unitree_webrtc_connect/multicast_scanner.py
unitree_webrtc_connect/unitree_auth.py
unitree_webrtc_connect/util.py
unitree_webrtc_connect/webrtc_audio.py
unitree_webrtc_connect/webrtc_audiohub.py
unitree_webrtc_connect/webrtc_datachannel.py
unitree_webrtc_connect/webrtc_driver.py
unitree_webrtc_connect/webrtc_video.py
unitree_webrtc_connect/lidar/libvoxel.wasm
unitree_webrtc_connect/lidar/lidar_decoder_libvoxel.py
unitree_webrtc_connect/lidar/lidar_decoder_native.py
unitree_webrtc_connect/lidar/lidar_decoder_unified.py
unitree_webrtc_connect/msgs/error_handler.py
unitree_webrtc_connect/msgs/future_resolver.py
unitree_webrtc_connect/msgs/heartbeat.py
unitree_webrtc_connect/msgs/pub_sub.py
unitree_webrtc_connect/msgs/rtc_inner_req.py
unitree_webrtc_connect/msgs/validation.py
unitree_webrtc_connect_leshy-2.0.7.dist-info/licenses/LICENSE
unitree_webrtc_connect_leshy-2.0.7.dist-info/METADATA
unitree_webrtc_connect_leshy-2.0.7.dist-info/WHEEL
unitree_webrtc_connect_leshy-2.0.7.dist-info/top_level.txt
unitree_webrtc_connect_leshy-2.0.7.dist-info/RECORD
