Metadata-Version: 2.4
Name: unitree_webrtc_connect_leshy
Version: 2.0.7
Summary: Connect to the Unitree Go2 and G1 with WebRTC
Author-email: legion1581 <legion1581@gmail.com>
Requires-Python: >=3.8
License-File: LICENSE
Requires-Dist: aiortc>=1.9.0
Requires-Dist: pycryptodome
Requires-Dist: requests
Requires-Dist: wasmtime
Requires-Dist: flask-socketio
Requires-Dist: lz4
Requires-Dist: numpy
Requires-Dist: packaging
Requires-Dist: sounddevice
Requires-Dist: pyaudio
Requires-Dist: pydub
Requires-Dist: opencv-python
Dynamic: license-file
